[
  {
    "confirm_code": "0038L00000Ek5iyQAB",
    "account_id": "0018L00000L3GVXQA3",
    "user_name": "0058L000001UCcCQAW",
    "title": "Mr",
    "first_name": "CTM Par",
    "last_name": "Full GRM Access",
    "email_id": "muhammad.salman.one@wnco.com",
    "user_address": "4016 Doane Street, Phoenix, CA 94538",
    "country_code": "US",
    "city_id": "Phoenix",
    "user_zip_code": 94538,
    "phone_number": "555-000-48027",
    "approved_status": "Y"
  },
  {
    "confirm_code": "0038L00000Ek5qrQAB",
    "account_id": "0018L00000L3GVXQA3",
    "user_name": "0058L000001UDISQA4",
    "title": "Mr",
    "first_name": "CTM Par",
    "last_name": "Full No GRM Access",
    "email_id": "muhammad.salman.two@wnco.com",
    "user_address": "4016 Doane Street, Phoenix, CA 94538",
    "country_code": "US",
    "city_id": "Phoenix",
    "user_zip_code": 94538,
    "phone_number": "555-000-48027",
    "approved_status": "Y"
  },
  {
    "confirm_code": "0038L00000Ek5rkQAB",
    "account_id": "0018L00000L3M3sQAF",
    "user_name": "0058L000001UDIXQA4",
    "title": "Mr",
    "first_name": "CTM Sub",
    "last_name": "Full GRM Access",
    "email_id": "muhammad.salman.three@wnco.com",
    "user_address": "4016 Doane Street, Phoenix, CA 94538",
    "country_code": "US",
    "city_id": "Phoenix",
    "user_zip_code": 94538,
    "phone_number": "555-000-48027",
    "approved_status": "Y"
  },
  {
    "confirm_code": "0038L00000Ek5uFQAR",
    "account_id": "0018L00000L3M3sQAF",
    "user_name": "0058L000001UDIcQAO",
    "title": "Mr",
    "first_name": "CTM Sub",
    "last_name": "Limited GRM Access",
    "email_id": "muhammad.salman.four@wnco.com",
    "user_address": "4016 Doane Street, Phoenix, CA 94538",
    "country_code": "US",
    "city_id": "Phoenix",
    "user_zip_code": 94538,
    "phone_number": "555-000-48027",
    "approved_status": "Y"
  },
  {
    "confirm_code": "0038L00000Ek5vDQAR",
    "account_id": "0018L00000L3QubQAF",
    "user_name": "0058L000001UCcHQAW",
    "title": "Mr",
    "first_name": "TMC Par",
    "last_name": "Full GRM Access",
    "email_id": "muhammad.salman.five@wnco.com",
    "user_address": "4016 Doane Street, Phoenix, CA 94538",
    "country_code": "US",
    "city_id": "Phoenix",
    "user_zip_code": 94538,
    "phone_number": "555-000-48027",
    "approved_status": "Y"
  }
]
